autort/__init__.py
autort/main.py
autort/prompts.py
autort_swarms-0.0.6.dist-info/LICENSE
autort_swarms-0.0.6.dist-info/WHEEL
autort_swarms-0.0.6.dist-info/METADATA
autort_swarms-0.0.6.dist-info/RECORD
