Metadata-Version: 2.1
Name: autort-swarms
Version: 0.0.6
Summary: AutoRT - Pytorch
Home-page: https://github.com/kyegomez/AutoRT
License: MIT
Keywords: artificial intelligence,deep learning,optimizers,Prompt Engineering
Author: Kye Gomez
Author-email: kye@apac.ai
Requires-Python: >=3.6,<4.0
Classifier: Development Status :: 4 - Beta
Classifier: Intended Audience :: Developers
Classifier: License :: OSI Approved :: MIT License
Classifier: Programming Language :: Python :: 3
Classifier: Programming Language :: Python :: 3.6
Classifier: Programming Language :: Python :: 3.7
Classifier: Programming Language :: Python :: 3.8
Classifier: Programming Language :: Python :: 3.9
Classifier: Programming Language :: Python :: 3.10
Classifier: Programming Language :: Python :: 3.11
Classifier: Programming Language :: Python :: 3.9
Classifier: Topic :: Scientific/Engineering :: Artificial Intelligence
Requires-Dist: einops
Requires-Dist: swarms
Requires-Dist: torch (>=1.9.0,<2.0.0)
Requires-Dist: torchvision (>=0.10.0,<0.11.0)
Requires-Dist: zetascale
Project-URL: Documentation, https://github.com/kyegomez/AutoRT
Project-URL: Repository, https://github.com/kyegomez/AutoRT
